<DOCUMENT>
    <item>
        <display>
            <title>Noble新能源</title>
            <pc_brand_url>https://www.dongchedi.com/auto/library/x-x-x-x-x-x-x-x-x-x-x?key=brand&amp;param=276&amp;text=Noble</pc_brand_url>
            <lightappid_brand_url>tt3ed7486aa1fd80c3</lightappid_brand_url>
            <brand_url>https://m.dcdapp.com/motor/m/car_series/list?zt=tt_search_brand&amp;brand_id=276</brand_url>
            <sub_brands>
                <item>
                    <tag>跑车</tag>
                    <sub_brand_name>Noble新能源</sub_brand_name>
                    <series_list>
                        <item>
                            <pc_pic_url>https://www.dongchedi.com/auto/series/5797/images</pc_pic_url>
                            <series_brand>Noble</series_brand>
                            <hot>21</hot>
                            <series_type>4</series_type>
                            <price>未上市</price>
                            <series_name>Noble M500</series_name>
                            <lightapp_pic_url>pages/atlas?series_id=5797&amp;zt=tt_search_brand&amp;series_name=Noble%20M500</lightapp_pic_url>
                            <cover_url>http://p6-dcd.byteimg.com/img/motor-img/d008c2820b51f3f8116ca1c89c4b20ac~240x0.png</cover_url>
                            <lightappid_pic_url>tt3ed7486aa1fd80c3</lightappid_pic_url>
                            <series_id>5797</series_id>
                            <pc_detail_url>https://www.dongchedi.com/auto/series/5797</pc_detail_url>
                            <lightappid_detail_url>tt3ed7486aa1fd80c3</lightappid_detail_url>
                            <series_offline>0</series_offline>
                            <lightapp_detail_url>pages/seriesIndex?series_id=5797&amp;zt=tt_search_brand&amp;series_name=Noble%20M500</lightapp_detail_url>
                            <detail_url>https://m.dcdapp.com/motor/m/car_series/index?zt=tt_search_brand&amp;series_id=5797</detail_url>
                            <pic_url>https://m.dcdapp.com/motor/m/car_series/atlas?zt=tt_search_brand&amp;series_id=5797&amp;category=wg</pic_url>
                        </item>
                        <item>
                            <pc_pic_url>https://www.dongchedi.com/auto/series/3603/images</pc_pic_url>
                            <series_brand>Noble</series_brand>
                            <hot>18</hot>
                            <series_type>4</series_type>
                            <price>未上市</price>
                            <series_name>Noble M600</series_name>
                            <lightapp_pic_url>pages/atlas?series_id=3603&amp;zt=tt_search_brand&amp;series_name=Noble%20M600</lightapp_pic_url>
                            <cover_url>http://p9-dcd.byteimg.com/img/mosaic-legacy/bef00000dac6f612be13~240x0.png</cover_url>
                            <lightappid_pic_url>tt3ed7486aa1fd80c3</lightappid_pic_url>
                            <series_id>3603</series_id>
                            <pc_detail_url>https://www.dongchedi.com/auto/series/3603</pc_detail_url>
                            <lightappid_detail_url>tt3ed7486aa1fd80c3</lightappid_detail_url>
                            <series_offline>0</series_offline>
                            <lightapp_detail_url>pages/seriesIndex?series_id=3603&amp;zt=tt_search_brand&amp;series_name=Noble%20M600</lightapp_detail_url>
                            <detail_url>https://m.dcdapp.com/motor/m/car_series/index?zt=tt_search_brand&amp;series_id=3603</detail_url>
                            <pic_url>https://m.dcdapp.com/motor/m/car_series/atlas?zt=tt_search_brand&amp;series_id=3603&amp;category=wg</pic_url>
                        </item>
                    </series_list>
                </item>
            </sub_brands>
            <lightapp_brand_url>pages/seriesList?zt=tt_search_brand&amp;brand_id=276&amp;brand_name=Noble</lightapp_brand_url>
        </display>
        <key>noble新能源</key>
    </item>
    <item>
        <display>
            <title>霍顿新能源</title>
            <pc_brand_url>https://www.dongchedi.com/auto/library/x-x-x-x-x-x-x-x-x-x-x?key=brand&amp;param=278&amp;text=霍顿</pc_brand_url>
            <lightappid_brand_url>tt3ed7486aa1fd80c3</lightappid_brand_url>
            <brand_url>https://m.dcdapp.com/motor/m/car_series/list?zt=tt_search_brand&amp;brand_id=278</brand_url>
            <sub_brands>
                <item>
                    <tag>热门</tag>
                    <sub_brand_name>霍顿新能源</sub_brand_name>
                    <series_list>
                        <item>
                            <pc_pic_url>https://www.dongchedi.com/auto/series/3629/images</pc_pic_url>
                            <series_brand>霍顿</series_brand>
                            <hot>156</hot>
                            <series_type>0</series_type>
                            <price>未上市</price>
                            <series_name>Commodore</series_name>
                            <lightapp_pic_url>pages/atlas?series_id=3629&amp;zt=tt_search_brand&amp;series_name=Commodore</lightapp_pic_url>
                            <cover_url>http://p6-dcd.byteimg.com/img/mosaic-legacy/bef40000602f52beeb0e~240x0.png</cover_url>
                            <lightappid_pic_url>tt3ed7486aa1fd80c3</lightappid_pic_url>
                            <series_id>3629</series_id>
                            <pc_detail_url>https://www.dongchedi.com/auto/series/3629</pc_detail_url>
                            <lightappid_detail_url>tt3ed7486aa1fd80c3</lightappid_detail_url>
                            <series_offline>0</series_offline>
                            <lightapp_detail_url>pages/seriesIndex?series_id=3629&amp;zt=tt_search_brand&amp;series_name=Commodore</lightapp_detail_url>
                            <detail_url>https://m.dcdapp.com/motor/m/car_series/index?zt=tt_search_brand&amp;series_id=3629</detail_url>
                            <pic_url>https://m.dcdapp.com/motor/m/car_series/atlas?zt=tt_search_brand&amp;series_id=3629&amp;category=wg</pic_url>
                        </item>
                        <item>
                            <pc_pic_url>https://www.dongchedi.com/auto/series/3630/images</pc_pic_url>
                            <series_brand>霍顿</series_brand>
                            <hot>83</hot>
                            <series_type>1</series_type>
                            <price>未上市</price>
                            <series_name>霍顿Trailblazer</series_name>
                            <lightapp_pic_url>pages/atlas?series_id=3630&amp;zt=tt_search_brand&amp;series_name=%E9%9C%8D%E9%A1%BFTrailblazer</lightapp_pic_url>
                            <cover_url>http://p9-dcd.byteimg.com/img/mosaic-legacy/bef20000df2de364bea0~240x0.png</cover_url>
                            <lightappid_pic_url>tt3ed7486aa1fd80c3</lightappid_pic_url>
                            <series_id>3630</series_id>
                            <pc_detail_url>https://www.dongchedi.com/auto/series/3630</pc_detail_url>
                            <lightappid_detail_url>tt3ed7486aa1fd80c3</lightappid_detail_url>
                            <series_offline>0</series_offline>
                            <lightapp_detail_url>pages/seriesIndex?series_id=3630&amp;zt=tt_search_brand&amp;series_name=%E9%9C%8D%E9%A1%BFTrailblazer</lightapp_detail_url>
                            <detail_url>https://m.dcdapp.com/motor/m/car_series/index?zt=tt_search_brand&amp;series_id=3630</detail_url>
                            <pic_url>https://m.dcdapp.com/motor/m/car_series/atlas?zt=tt_search_brand&amp;series_id=3630&amp;category=wg</pic_url>
                        </item>
                        <item>
                            <pc_pic_url>https://www.dongchedi.com/auto/series/3631/images</pc_pic_url>
                            <series_brand>霍顿</series_brand>
                            <hot>36</hot>
                            <series_type>3</series_type>
                            <price>未上市</price>
                            <series_name>霍顿Colorado</series_name>
                            <lightapp_pic_url>pages/atlas?series_id=3631&amp;zt=tt_search_brand&amp;series_name=%E9%9C%8D%E9%A1%BFColorado</lightapp_pic_url>
                            <cover_url>http://p6-dcd.byteimg.com/img/mosaic-legacy/bef20000df2ef5b56a9b~240x0.png</cover_url>
                            <lightappid_pic_url>tt3ed7486aa1fd80c3</lightappid_pic_url>
                            <series_id>3631</series_id>
                            <pc_detail_url>https://www.dongchedi.com/auto/series/3631</pc_detail_url>
                            <lightappid_detail_url>tt3ed7486aa1fd80c3</lightappid_detail_url>
                            <series_offline>0</series_offline>
                            <lightapp_detail_url>pages/seriesIndex?series_id=3631&amp;zt=tt_search_brand&amp;series_name=%E9%9C%8D%E9%A1%BFColorado</lightapp_detail_url>
                            <detail_url>https://m.dcdapp.com/motor/m/car_series/index?zt=tt_search_brand&amp;series_id=3631</detail_url>
                            <pic_url>https://m.dcdapp.com/motor/m/car_series/atlas?zt=tt_search_brand&amp;series_id=3631&amp;category=wg</pic_url>
                        </item>
                    </series_list>
                </item>
                <item>
                    <tag>轿车</tag>
                    <sub_brand_name>霍顿新能源</sub_brand_name>
                    <series_list>
                        <item>
                            <pc_pic_url>https://www.dongchedi.com/auto/series/3629/images</pc_pic_url>
                            <series_brand>霍顿</series_brand>
                            <hot>156</hot>
                            <series_type>0</series_type>
                            <price>未上市</price>
                            <series_name>Commodore</series_name>
                            <lightapp_pic_url>pages/atlas?series_id=3629&amp;zt=tt_search_brand&amp;series_name=Commodore</lightapp_pic_url>
                            <cover_url>http://p6-dcd.byteimg.com/img/mosaic-legacy/bef40000602f52beeb0e~240x0.png</cover_url>
                            <lightappid_pic_url>tt3ed7486aa1fd80c3</lightappid_pic_url>
                            <series_id>3629</series_id>
                            <pc_detail_url>https://www.dongchedi.com/auto/series/3629</pc_detail_url>
                            <lightappid_detail_url>tt3ed7486aa1fd80c3</lightappid_detail_url>
                            <series_offline>0</series_offline>
                            <lightapp_detail_url>pages/seriesIndex?series_id=3629&amp;zt=tt_search_brand&amp;series_name=Commodore</lightapp_detail_url>
                            <detail_url>https://m.dcdapp.com/motor/m/car_series/index?zt=tt_search_brand&amp;series_id=3629</detail_url>
                            <pic_url>https://m.dcdapp.com/motor/m/car_series/atlas?zt=tt_search_brand&amp;series_id=3629&amp;category=wg</pic_url>
                        </item>
                    </series_list>
                </item>
                <item>
                    <tag>SUV</tag>
                    <sub_brand_name>霍顿新能源</sub_brand_name>
                    <series_list>
                        <item>
                            <pc_pic_url>https://www.dongchedi.com/auto/series/3630/images</pc_pic_url>
                            <series_brand>霍顿</series_brand>
                            <hot>83</hot>
                            <series_type>1</series_type>
                            <price>未上市</price>
                            <series_name>霍顿Trailblazer</series_name>
                            <lightapp_pic_url>pages/atlas?series_id=3630&amp;zt=tt_search_brand&amp;series_name=%E9%9C%8D%E9%A1%BFTrailblazer</lightapp_pic_url>
                            <cover_url>http://p9-dcd.byteimg.com/img/mosaic-legacy/bef20000df2de364bea0~240x0.png</cover_url>
                            <lightappid_pic_url>tt3ed7486aa1fd80c3</lightappid_pic_url>
                            <series_id>3630</series_id>
                            <pc_detail_url>https://www.dongchedi.com/auto/series/3630</pc_detail_url>
                            <lightappid_detail_url>tt3ed7486aa1fd80c3</lightappid_detail_url>
                            <series_offline>0</series_offline>
                            <lightapp_detail_url>pages/seriesIndex?series_id=3630&amp;zt=tt_search_brand&amp;series_name=%E9%9C%8D%E9%A1%BFTrailblazer</lightapp_detail_url>
                            <detail_url>https://m.dcdapp.com/motor/m/car_series/index?zt=tt_search_brand&amp;series_id=3630</detail_url>
                            <pic_url>https://m.dcdapp.com/motor/m/car_series/atlas?zt=tt_search_brand&amp;series_id=3630&amp;category=wg</pic_url>
                        </item>
                    </series_list>
                </item>
                <item>
                    <tag>皮卡</tag>
                    <sub_brand_name>霍顿新能源</sub_brand_name>
                    <series_list>
                        <item>
                            <pc_pic_url>https://www.dongchedi.com/auto/series/3631/images</pc_pic_url>
                            <series_brand>霍顿</series_brand>
                            <hot>36</hot>
                            <series_type>3</series_type>
                            <price>未上市</price>
                            <series_name>霍顿Colorado</series_name>
                            <lightapp_pic_url>pages/atlas?series_id=3631&amp;zt=tt_search_brand&amp;series_name=%E9%9C%8D%E9%A1%BFColorado</lightapp_pic_url>
                            <cover_url>http://p3-dcd.byteimg.com/img/mosaic-legacy/bef20000df2ef5b56a9b~240x0.png</cover_url>
                            <lightappid_pic_url>tt3ed7486aa1fd80c3</lightappid_pic_url>
                            <series_id>3631</series_id>
                            <pc_detail_url>https://www.dongchedi.com/auto/series/3631</pc_detail_url>
                            <lightappid_detail_url>tt3ed7486aa1fd80c3</lightappid_detail_url>
                            <series_offline>0</series_offline>
                            <lightapp_detail_url>pages/seriesIndex?series_id=3631&amp;zt=tt_search_brand&amp;series_name=%E9%9C%8D%E9%A1%BFColorado</lightapp_detail_url>
                            <detail_url>https://m.dcdapp.com/motor/m/car_series/index?zt=tt_search_brand&amp;series_id=3631</detail_url>
                            <pic_url>https://m.dcdapp.com/motor/m/car_series/atlas?zt=tt_search_brand&amp;series_id=3631&amp;category=wg</pic_url>
                        </item>
                    </series_list>
                </item>
            </sub_brands>
            <lightapp_brand_url>pages/seriesList?zt=tt_search_brand&amp;brand_id=278&amp;brand_name=%E9%9C%8D%E9%A1%BF</lightapp_brand_url>
        </display>
        <key>霍顿新能源</key>
    </item>
    <item>
        <display>
            <title>星途新能源</title>
            <pc_brand_url>https://www.dongchedi.com/auto/library/x-x-x-x-x-x-x-x-x-x-x?key=brand&amp;param=251&amp;text=星途</pc_brand_url>
            <lightappid_brand_url>tt3ed7486aa1fd80c3</lightappid_brand_url>
            <brand_url>https://m.dcdapp.com/motor/m/car_series/list?zt=tt_search_brand&amp;brand_id=251</brand_url>
            <sub_brands>
                <item>
                    <tag>SUV</tag>
                    <sub_brand_name>星途新能源</sub_brand_name>
                    <series_list>
                        <item>
                            <pc_pic_url>https://www.dongchedi.com/auto/series/5567/images</pc_pic_url>
                            <series_brand>星途</series_brand>
                            <hot>21699</hot>
                            <series_type>1</series_type>
                            <price>14.98万起</price>
                            <series_name>星途追风ET-i</series_name>
                            <lightapp_pic_url>pages/atlas?series_id=5567&amp;zt=tt_search_brand&amp;series_name=%E6%98%9F%E9%80%94%E8%BF%BD%E9%A3%8EET-i</lightapp_pic_url>
                            <cover_url>http://p9-dcd.byteimg.com/img/motor-img/d26d891e3dc35bc86a3bb4f730e6d8dd~240x0.png</cover_url>
                            <lightappid_pic_url>tt3ed7486aa1fd80c3</lightappid_pic_url>
                            <series_id>5567</series_id>
                            <pc_detail_url>https://www.dongchedi.com/auto/series/5567</pc_detail_url>
                            <lightappid_detail_url>tt3ed7486aa1fd80c3</lightappid_detail_url>
                            <series_offline>0</series_offline>
                            <lightapp_detail_url>pages/seriesIndex?series_id=5567&amp;zt=tt_search_brand&amp;series_name=%E6%98%9F%E9%80%94%E8%BF%BD%E9%A3%8EET-i</lightapp_detail_url>
                            <detail_url>https://m.dcdapp.com/motor/m/car_series/index?zt=tt_search_brand&amp;series_id=5567</detail_url>
                            <pic_url>https://m.dcdapp.com/motor/m/car_series/atlas?zt=tt_search_brand&amp;series_id=5567&amp;category=wg</pic_url>
                        </item>
                        <item>
                            <pc_pic_url>https://www.dongchedi.com/auto/series/3436/images</pc_pic_url>
                            <series_brand>星途</series_brand>
                            <hot>630</hot>
                            <series_type>1</series_type>
                            <price>未上市</price>
                            <series_name>星途E-IUV</series_name>
                            <lightapp_pic_url>pages/atlas?series_id=3436&amp;zt=tt_search_brand&amp;series_name=%E6%98%9F%E9%80%94E-IUV</lightapp_pic_url>
                            <cover_url>http://p1-dcd.byteimg.com/img/mosaic-legacy/bef800006724a609018f~240x0.png</cover_url>
                            <lightappid_pic_url>tt3ed7486aa1fd80c3</lightappid_pic_url>
                            <series_id>3436</series_id>
                            <pc_detail_url>https://www.dongchedi.com/auto/series/3436</pc_detail_url>
                            <lightappid_detail_url>tt3ed7486aa1fd80c3</lightappid_detail_url>
                            <series_offline>0</series_offline>
                            <lightapp_detail_url>pages/seriesIndex?series_id=3436&amp;zt=tt_search_brand&amp;series_name=%E6%98%9F%E9%80%94E-IUV</lightapp_detail_url>
                            <detail_url>https://m.dcdapp.com/motor/m/car_series/index?zt=tt_search_brand&amp;series_id=3436</detail_url>
                            <pic_url>https://m.dcdapp.com/motor/m/car_series/atlas?zt=tt_search_brand&amp;series_id=3436&amp;category=wg</pic_url>
                        </item>
                        <item>
                            <pc_pic_url>https://www.dongchedi.com/auto/series/5095/images</pc_pic_url>
                            <series_brand>星途</series_brand>
                            <hot>508</hot>
                            <series_type>1</series_type>
                            <price>未上市</price>
                            <series_name>瑶光</series_name>
                            <lightapp_pic_url>pages/atlas?series_id=5095&amp;zt=tt_search_brand&amp;series_name=%E7%91%B6%E5%85%89</lightapp_pic_url>
                            <cover_url>http://p3-dcd.byteimg.com/img/motor-img/bbfeae4c5cbd610de518c57e446763ce~240x0.png</cover_url>
                            <lightappid_pic_url>tt3ed7486aa1fd80c3</lightappid_pic_url>
                            <series_id>5095</series_id>
                            <pc_detail_url>https://www.dongchedi.com/auto/series/5095</pc_detail_url>
                            <lightappid_detail_url>tt3ed7486aa1fd80c3</lightappid_detail_url>
                            <series_offline>0</series_offline>
                            <lightapp_detail_url>pages/seriesIndex?series_id=5095&amp;zt=tt_search_brand&amp;series_name=%E7%91%B6%E5%85%89</lightapp_detail_url>
                            <detail_url>https://m.dcdapp.com/motor/m/car_series/index?zt=tt_search_brand&amp;series_id=5095</detail_url>
                            <pic_url>https://m.dcdapp.com/motor/m/car_series/atlas?zt=tt_search_brand&amp;series_id=5095&amp;category=wg</pic_url>
                        </item>
                    </series_list>
                </item>
            </sub_brands>
            <lightapp_brand_url>pages/seriesList?zt=tt_search_brand&amp;brand_id=251&amp;brand_name=%E6%98%9F%E9%80%94</lightapp_brand_url>
        </display>
        <key>星途新能源</key>
    </item>
    <item>
        <display>
            <title>SINCARS新能源</title>
            <pc_brand_url>https://www.dongchedi.com/auto/library/x-x-x-x-x-x-x-x-x-x-x?key=brand&amp;param=360&amp;text=SIN CARS</pc_brand_url>
            <lightappid_brand_url>tt3ed7486aa1fd80c3</lightappid_brand_url>
            <brand_url>https://m.dcdapp.com/motor/m/car_series/list?zt=tt_search_brand&amp;brand_id=360</brand_url>
            <sub_brands>
                <item>
                    <tag>跑车</tag>
                    <sub_brand_name>SINCARS新能源</sub_brand_name>
                    <series_list>
                        <item>
                            <pc_pic_url>https://www.dongchedi.com/auto/series/4265/images</pc_pic_url>
                            <series_brand>SIN CARS</series_brand>
                            <hot>18</hot>
                            <series_type>4</series_type>
                            <price>未上市</price>
                            <series_name>SIN R1</series_name>
                            <lightapp_pic_url>pages/atlas?series_id=4265&amp;zt=tt_search_brand&amp;series_name=SIN%20R1</lightapp_pic_url>
                            <cover_url>http://p9-dcd.byteimg.com/img/motor-img/11f716f20e825c56f1e8bdace83d2c0e~240x0.png</cover_url>
                            <lightappid_pic_url>tt3ed7486aa1fd80c3</lightappid_pic_url>
                            <series_id>4265</series_id>
                            <pc_detail_url>https://www.dongchedi.com/auto/series/4265</pc_detail_url>
                            <lightappid_detail_url>tt3ed7486aa1fd80c3</lightappid_detail_url>
                            <series_offline>0</series_offline>
                            <lightapp_detail_url>pages/seriesIndex?series_id=4265&amp;zt=tt_search_brand&amp;series_name=SIN%20R1</lightapp_detail_url>
                            <detail_url>https://m.dcdapp.com/motor/m/car_series/index?zt=tt_search_brand&amp;series_id=4265</detail_url>
                            <pic_url>https://m.dcdapp.com/motor/m/car_series/atlas?zt=tt_search_brand&amp;series_id=4265&amp;category=wg</pic_url>
                        </item>
                    </series_list>
                </item>
            </sub_brands>
            <lightapp_brand_url>pages/seriesList?zt=tt_search_brand&amp;brand_id=360&amp;brand_name=SIN%20CARS</lightapp_brand_url>
        </display>
        <key>sincars新能源</key>
    </item>
    <item>
        <display>
            <title>广汽埃安新能源</title>
            <pc_brand_url>https://www.dongchedi.com/auto/library/x-x-x-x-x-x-x-x-x-x-x?key=brand&amp;param=242&amp;text=广汽埃安</pc_brand_url>
            <lightappid_brand_url>tt3ed7486aa1fd80c3</lightappid_brand_url>
            <brand_url>https://m.dcdapp.com/motor/m/car_series/list?zt=tt_search_brand&amp;brand_id=242</brand_url>
            <sub_brands>
                <item>
                    <tag>热门</tag>
                    <sub_brand_name>广汽埃安新能源</sub_brand_name>
                    <series_list>
                        <item>
                            <pc_pic_url>https://www.dongchedi.com/auto/series/3101/images</pc_pic_url>
                            <series_brand>广汽埃安新能源</series_brand>
                            <hot>80953</hot>
                            <series_type>0</series_type>
                            <price>13.96万起</price>
                            <series_name>AION S</series_name>
                            <lightapp_pic_url>pages/atlas?series_id=3101&amp;zt=tt_search_brand&amp;series_name=AION%20S</lightapp_pic_url>
                            <cover_url>http://p3-dcd.byteimg.com/img/motor-img/7d99d3eef9fba8765615b27ad9825cd7~240x0.png</cover_url>
                            <lightappid_pic_url>tt3ed7486aa1fd80c3</lightappid_pic_url>
                            <series_id>3101</series_id>
                            <pc_detail_url>https://www.dongchedi.com/auto/series/3101</pc_detail_url>
                            <lightappid_detail_url>tt3ed7486aa1fd80c3</lightappid_detail_url>
                            <series_offline>0</series_offline>
                            <lightapp_detail_url>pages/seriesIndex?series_id=3101&amp;zt=tt_search_brand&amp;series_name=AION%20S</lightapp_detail_url>
                            <detail_url>https://m.dcdapp.com/motor/m/car_series/index?zt=tt_search_brand&amp;series_id=3101</detail_url>
                            <pic_url>https://m.dcdapp.com/motor/m/car_series/atlas?zt=tt_search_brand&amp;series_id=3101&amp;category=wg</pic_url>
                        </item>
                        <item>
                            <pc_pic_url>https://www.dongchedi.com/auto/series/4814/images</pc_pic_url>
                            <series_brand>广汽埃安新能源</series_brand>
                            <hot>79254</hot>
                            <series_type>1</series_type>
                            <price>10.46万起</price>
                            <series_name>AION Y</series_name>
                            <lightapp_pic_url>pages/atlas?series_id=4814&amp;zt=tt_search_brand&amp;series_name=AION%20Y</lightapp_pic_url>
                            <cover_url>http://p6-dcd.byteimg.com/img/motor-img/a5fa6ea169e529ef121b4d128912c523~240x0.png</cover_url>
                            <lightappid_pic_url>tt3ed7486aa1fd80c3</lightappid_pic_url>
                            <series_id>4814</series_id>
                            <pc_detail_url>https://www.dongchedi.com/auto/series/4814</pc_detail_url>
                            <lightappid_detail_url>tt3ed7486aa1fd80c3</lightappid_detail_url>
                            <series_offline>0</series_offline>
                            <lightapp_detail_url>pages/seriesIndex?series_id=4814&amp;zt=tt_search_brand&amp;series_name=AION%20Y</lightapp_detail_url>
                            <detail_url>https://m.dcdapp.com/motor/m/car_series/index?zt=tt_search_brand&amp;series_id=4814</detail_url>
                            <pic_url>https://m.dcdapp.com/motor/m/car_series/atlas?zt=tt_search_brand&amp;series_id=4814&amp;category=wg</pic_url>
                        </item>
                        <item>
                            <pc_pic_url>https://www.dongchedi.com/auto/series/4426/images</pc_pic_url>
                            <series_brand>广汽埃安新能源</series_brand>
                            <hot>29613</hot>
                            <series_type>1</series_type>
                            <price>17.76万起</price>
                            <series_name>AION V</series_name>
                            <lightapp_pic_url>pages/atlas?series_id=4426&amp;zt=tt_search_brand&amp;series_name=AION%20V</lightapp_pic_url>
                            <cover_url>http://p9-dcd.byteimg.com/img/motor-img/0657da7550d5af0260ddc50c678e8c40~240x0.png</cover_url>
                            <lightappid_pic_url>tt3ed7486aa1fd80c3</lightappid_pic_url>
                            <series_id>4426</series_id>
                            <pc_detail_url>https://www.dongchedi.com/auto/series/4426</pc_detail_url>
                            <lightappid_detail_url>tt3ed7486aa1fd80c3</lightappid_detail_url>
                            <series_offline>0</series_offline>
                            <lightapp_detail_url>pages/seriesIndex?series_id=4426&amp;zt=tt_search_brand&amp;series_name=AION%20V</lightapp_detail_url>
                            <detail_url>https://m.dcdapp.com/motor/m/car_series/index?zt=tt_search_brand&amp;series_id=4426</detail_url>
                            <pic_url>https://m.dcdapp.com/motor/m/car_series/atlas?zt=tt_search_brand&amp;series_id=4426&amp;category=wg</pic_url>
                        </item>
                        <item>
                            <pc_pic_url>https://www.dongchedi.com/auto/series/3503/images</pc_pic_url>
                            <series_brand>广汽埃安新能源</series_brand>
                            <hot>18517</hot>
                            <series_type>1</series_type>
                            <price>28.66万起</price>
                            <series_name>AION LX</series_name>
                            <lightapp_pic_url>pages/atlas?series_id=3503&amp;zt=tt_search_brand&amp;series_name=AION%20LX</lightapp_pic_url>
                            <cover_url>http://p9-dcd.byteimg.com/img/motor-img/a3dad86701857afacb920e7123c4df1c~240x0.png</cover_url>
                            <lightappid_pic_url>tt3ed7486aa1fd80c3</lightappid_pic_url>
                            <series_id>3503</series_id>
                            <pc_detail_url>https://www.dongchedi.com/auto/series/3503</pc_detail_url>
                            <lightappid_detail_url>tt3ed7486aa1fd80c3</lightappid_detail_url>
                            <series_offline>0</series_offline>
                            <lightapp_detail_url>pages/seriesIndex?series_id=3503&amp;zt=tt_search_brand&amp;series_name=AION%20LX</lightapp_detail_url>
                            <detail_url>https://m.dcdapp.com/motor/m/car_series/index?zt=tt_search_brand&amp;series_id=3503</detail_url>
                            <pic_url>https://m.dcdapp.com/motor/m/car_series/atlas?zt=tt_search_brand&amp;series_id=3503&amp;category=wg</pic_url>
                        </item>
                        <item>
                            <pc_pic_url>https://www.dongchedi.com/auto/series/1598/images</pc_pic_url>
                            <series_brand>广汽埃安新能源</series_brand>
                            <hot>3839</hot>
                            <series_type>1</series_type>
                            <price>12.98万起</price>
                            <series_name>传祺GE3</series_name>
                            <lightapp_pic_url>pages/atlas?series_id=1598&amp;zt=tt_search_brand&amp;series_name=%E4%BC%A0%E7%A5%BAGE3</lightapp_pic_url>
                            <cover_url>http://p6-dcd.byteimg.com/img/mosaic-legacy/beef0000981a1ee73393~240x0.png</cover_url>
                            <lightappid_pic_url>tt3ed7486aa1fd80c3</lightappid_pic_url>
                            <series_id>1598</series_id>
                            <pc_detail_url>https://www.dongchedi.com/auto/series/1598</pc_detail_url>
                            <lightappid_detail_url>tt3ed7486aa1fd80c3</lightappid_detail_url>
                            <series_offline>0</series_offline>
                            <lightapp_detail_url>pages/seriesIndex?series_id=1598&amp;zt=tt_search_brand&amp;series_name=%E4%BC%A0%E7%A5%BAGE3</lightapp_detail_url>
                            <detail_url>https://m.dcdapp.com/motor/m/car_series/index?zt=tt_search_brand&amp;series_id=1598</detail_url>
                            <pic_url>https://m.dcdapp.com/motor/m/car_series/atlas?zt=tt_search_brand&amp;series_id=1598&amp;category=wg</pic_url>
                        </item>
                        <item>
                            <pc_pic_url>https://www.dongchedi.com/auto/series/3793/images</pc_pic_url>
                            <series_brand>广汽埃安新能源</series_brand>
                            <hot>251</hot>
                            <series_type>0</series_type>
                            <price>未上市</price>
                            <series_name>广汽新能源2U</series_name>
                            <lightapp_pic_url>pages/atlas?series_id=3793&amp;zt=tt_search_brand&amp;series_name=%E5%B9%BF%E6%B1%BD%E6%96%B0%E8%83%BD%E6%BA%902U</lightapp_pic_url>
                            <cover_url>http://p6-dcd.byteimg.com/img/motor-img/4bb8a1e67cfcf35a0ff890fd89845ee3~240x0.png</cover_url>
                            <lightappid_pic_url>tt3ed7486aa1fd80c3</lightappid_pic_url>
                            <series_id>3793</series_id>
                            <pc_detail_url>https://www.dongchedi.com/auto/series/3793</pc_detail_url>
                            <lightappid_detail_url>tt3ed7486aa1fd80c3</lightappid_detail_url>
                            <series_offline>0</series_offline>
                            <lightapp_detail_url>pages/seriesIndex?series_id=3793&amp;zt=tt_search_brand&amp;series_name=%E5%B9%BF%E6%B1%BD%E6%96%B0%E8%83%BD%E6%BA%902U</lightapp_detail_url>
                            <detail_url>https://m.dcdapp.com/motor/m/car_series/index?zt=tt_search_brand&amp;series_id=3793</detail_url>
                            <pic_url>https://m.dcdapp.com/motor/m/car_series/atlas?zt=tt_search_brand&amp;series_id=3793&amp;category=wg</pic_url>
                        </item>
                        <item>
                            <pc_pic_url>https://www.dongchedi.com/auto/series/3368/images</pc_pic_url>
                            <series_brand>广汽埃安新能源</series_brand>
                            <hot>183</hot>
                            <series_type>1</series_type>
                            <price>未上市</price>
                            <series_name>ENTRANZE</series_name>
                            <lightapp_pic_url>pages/atlas?series_id=3368&amp;zt=tt_search_brand&amp;series_name=ENTRANZE</lightapp_pic_url>
                            <cover_url>http://p1-dcd.byteimg.com/img/mosaic-legacy/bef6000051281fce776c~240x0.png</cover_url>
                            <lightappid_pic_url>tt3ed7486aa1fd80c3</lightappid_pic_url>
                            <series_id>3368</series_id>
                            <pc_detail_url>https://www.dongchedi.com/auto/series/3368</pc_detail_url>
                            <lightappid_detail_url>tt3ed7486aa1fd80c3</lightappid_detail_url>
                            <series_offline>0</series_offline>
                            <lightapp_detail_url>pages/seriesIndex?series_id=3368&amp;zt=tt_search_brand&amp;series_name=ENTRANZE</lightapp_detail_url>
                            <detail_url>https://m.dcdapp.com/motor/m/car_series/index?zt=tt_search_brand&amp;series_id=3368</detail_url>
                            <pic_url>https://m.dcdapp.com/motor/m/car_series/atlas?zt=tt_search_brand&amp;series_id=3368&amp;category=wg</pic_url>
                        </item>
                    </series_list>
                </item>
                <item>
                    <tag>轿车</tag>
                    <sub_brand_name>广汽埃安新能源</sub_brand_name>
                    <series_list>
                        <item>
                            <pc_pic_url>https://www.dongchedi.com/auto/series/3101/images</pc_pic_url>
                            <series_brand>广汽埃安新能源</series_brand>
                            <hot>80953</hot>
                            <series_type>0</series_type>
                            <price>13.96万起</price>
                            <series_name>AION S</series_name>
                            <lightapp_pic_url>pages/atlas?series_id=3101&amp;zt=tt_search_brand&amp;series_name=AION%20S</lightapp_pic_url>
                            <cover_url>http://p6-dcd.byteimg.com/img/motor-img/7d99d3eef9fba8765615b27ad9825cd7~240x0.png</cover_url>
                            <lightappid_pic_url>tt3ed7486aa1fd80c3</lightappid_pic_url>
                            <series_id>3101</series_id>
                            <pc_detail_url>https://www.dongchedi.com/auto/series/3101</pc_detail_url>
                            <lightappid_detail_url>tt3ed7486aa1fd80c3</lightappid_detail_url>
                            <series_offline>0</series_offline>
                            <lightapp_detail_url>pages/seriesIndex?series_id=3101&amp;zt=tt_search_brand&amp;series_name=AION%20S</lightapp_detail_url>
                            <detail_url>https://m.dcdapp.com/motor/m/car_series/index?zt=tt_search_brand&amp;series_id=3101</detail_url>
                            <pic_url>https://m.dcdapp.com/motor/m/car_series/atlas?zt=tt_search_brand&amp;series_id=3101&amp;category=wg</pic_url>
                        </item>
                        <item>
                            <pc_pic_url>https://www.dongchedi.com/auto/series/3793/images</pc_pic_url>
                            <series_brand>广汽埃安新能源</series_brand>
                            <hot>251</hot>
                            <series_type>0</series_type>
                            <price>未上市</price>
                            <series_name>广汽新能源2U</series_name>
                            <lightapp_pic_url>pages/atlas?series_id=3793&amp;zt=tt_search_brand&amp;series_name=%E5%B9%BF%E6%B1%BD%E6%96%B0%E8%83%BD%E6%BA%902U</lightapp_pic_url>
                            <cover_url>http://p3-dcd.byteimg.com/img/motor-img/4bb8a1e67cfcf35a0ff890fd89845ee3~240x0.png</cover_url>
                            <lightappid_pic_url>tt3ed7486aa1fd80c3</lightappid_pic_url>
                            <series_id>3793</series_id>
                            <pc_detail_url>https://www.dongchedi.com/auto/series/3793</pc_detail_url>
                            <lightappid_detail_url>tt3ed7486aa1fd80c3</lightappid_detail_url>
                            <series_offline>0</series_offline>
                            <lightapp_detail_url>pages/seriesIndex?series_id=3793&amp;zt=tt_search_brand&amp;series_name=%E5%B9%BF%E6%B1%BD%E6%96%B0%E8%83%BD%E6%BA%902U</lightapp_detail_url>
                            <detail_url>https://m.dcdapp.com/motor/m/car_series/index?zt=tt_search_brand&amp;series_id=3793</detail_url>
                            <pic_url>https://m.dcdapp.com/motor/m/car_series/atlas?zt=tt_search_brand&amp;series_id=3793&amp;category=wg</pic_url>
                        </item>
                    </series_list>
                </item>
                <item>
                    <tag>SUV</tag>
                    <sub_brand_name>广汽埃安新能源</sub_brand_name>
                    <series_list>
                        <item>
                            <pc_pic_url>https://www.dongchedi.com/auto/series/4814/images</pc_pic_url>
                            <series_brand>广汽埃安新能源</series_brand>
                            <hot>79254</hot>
                            <series_type>1</series_type>
                            <price>10.46万起</price>
                            <series_name>AION Y</series_name>
                            <lightapp_pic_url>pages/atlas?series_id=4814&amp;zt=tt_search_brand&amp;series_name=AION%20Y</lightapp_pic_url>
                            <cover_url>http://p9-dcd.byteimg.com/img/motor-img/a5fa6ea169e529ef121b4d128912c523~240x0.png</cover_url>
                            <lightappid_pic_url>tt3ed7486aa1fd80c3</lightappid_pic_url>
                            <series_id>4814</series_id>
                            <pc_detail_url>https://www.dongchedi.com/auto/series/4814</pc_detail_url>
                            <lightappid_detail_url>tt3ed7486aa1fd80c3</lightappid_detail_url>
                            <series_offline>0</series_offline>
                            <lightapp_detail_url>pages/seriesIndex?series_id=4814&amp;zt=tt_search_brand&amp;series_name=AION%20Y</lightapp_detail_url>
                            <detail_url>https://m.dcdapp.com/motor/m/car_series/index?zt=tt_search_brand&amp;series_id=4814</detail_url>
                            <pic_url>https://m.dcdapp.com/motor/m/car_series/atlas?zt=tt_search_brand&amp;series_id=4814&amp;category=wg</pic_url>
                        </item>
                        <item>
                            <pc_pic_url>https://www.dongchedi.com/auto/series/4426/images</pc_pic_url>
                            <series_brand>广汽埃安新能源</series_brand>
                            <hot>29613</hot>
                            <series_type>1</series_type>
                            <price>17.76万起</price>
                            <series_name>AION V</series_name>
                            <lightapp_pic_url>pages/atlas?series_id=4426&amp;zt=tt_search_brand&amp;series_name=AION%20V</lightapp_pic_url>
                            <cover_url>http://p3-dcd.byteimg.com/img/motor-img/0657da7550d5af0260ddc50c678e8c40~240x0.png</cover_url>
                            <lightappid_pic_url>tt3ed7486aa1fd80c3</lightappid_pic_url>
                            <series_id>4426</series_id>
                            <pc_detail_url>https://www.dongchedi.com/auto/series/4426</pc_detail_url>
                            <lightappid_detail_url>tt3ed7486aa1fd80c3</lightappid_detail_url>
                            <series_offline>0</series_offline>
                            <lightapp_detail_url>pages/seriesIndex?series_id=4426&amp;zt=tt_search_brand&amp;series_name=AION%20V</lightapp_detail_url>
                            <detail_url>https://m.dcdapp.com/motor/m/car_series/index?zt=tt_search_brand&amp;series_id=4426</detail_url>
                            <pic_url>https://m.dcdapp.com/motor/m/car_series/atlas?zt=tt_search_brand&amp;series_id=4426&amp;category=wg</pic_url>
                        </item>
                        <item>
                            <pc_pic_url>https://www.dongchedi.com/auto/series/3503/images</pc_pic_url>
                            <series_brand>广汽埃安新能源</series_brand>
                            <hot>18517</hot>
                            <series_type>1</series_type>
                            <price>28.66万起</price>
                            <series_name>AION LX</series_name>
                            <lightapp_pic_url>pages/atlas?series_id=3503&amp;zt=tt_search_brand&amp;series_name=AION%20LX</lightapp_pic_url>
                            <cover_url>http://p3-dcd.byteimg.com/img/motor-img/a3dad86701857afacb920e7123c4df1c~240x0.png</cover_url>
                            <lightappid_pic_url>tt3ed7486aa1fd80c3</lightappid_pic_url>
                            <series_id>3503</series_id>
                            <pc_detail_url>https://www.dongchedi.com/auto/series/3503</pc_detail_url>
                            <lightappid_detail_url>tt3ed7486aa1fd80c3</lightappid_detail_url>
                            <series_offline>0</series_offline>
                            <lightapp_detail_url>pages/seriesIndex?series_id=3503&amp;zt=tt_search_brand&amp;series_name=AION%20LX</lightapp_detail_url>
                            <detail_url>https://m.dcdapp.com/motor/m/car_series/index?zt=tt_search_brand&amp;series_id=3503</detail_url>
                            <pic_url>https://m.dcdapp.com/motor/m/car_series/atlas?zt=tt_search_brand&amp;series_id=3503&amp;category=wg</pic_url>
                        </item>
                        <item>
                            <pc_pic_url>https://www.dongchedi.com/auto/series/1598/images</pc_pic_url>
                            <series_brand>广汽埃安新能源</series_brand>
                            <hot>3839</hot>
                            <series_type>1</series_type>
                            <price>12.98万起</price>
                            <series_name>传祺GE3</series_name>
                            <lightapp_pic_url>pages/atlas?series_id=1598&amp;zt=tt_search_brand&amp;series_name=%E4%BC%A0%E7%A5%BAGE3</lightapp_pic_url>
                            <cover_url>http://p1-dcd.byteimg.com/img/mosaic-legacy/beef0000981a1ee73393~240x0.png</cover_url>
                            <lightappid_pic_url>tt3ed7486aa1fd80c3</lightappid_pic_url>
                            <series_id>1598</series_id>
                            <pc_detail_url>https://www.dongchedi.com/auto/series/1598</pc_detail_url>
                            <lightappid_detail_url>tt3ed7486aa1fd80c3</lightappid_detail_url>
                            <series_offline>0</series_offline>
                            <lightapp_detail_url>pages/seriesIndex?series_id=1598&amp;zt=tt_search_brand&amp;series_name=%E4%BC%A0%E7%A5%BAGE3</lightapp_detail_url>
                            <detail_url>https://m.dcdapp.com/motor/m/car_series/index?zt=tt_search_brand&amp;series_id=1598</detail_url>
                            <pic_url>https://m.dcdapp.com/motor/m/car_series/atlas?zt=tt_search_brand&amp;series_id=1598&amp;category=wg</pic_url>
                        </item>
                        <item>
                            <pc_pic_url>https://www.dongchedi.com/auto/series/3368/images</pc_pic_url>
                            <series_brand>广汽埃安新能源</series_brand>
                            <hot>183</hot>
                            <series_type>1</series_type>
                            <price>未上市</price>
                            <series_name>ENTRANZE</series_name>
                            <lightapp_pic_url>pages/atlas?series_id=3368&amp;zt=tt_search_brand&amp;series_name=ENTRANZE</lightapp_pic_url>
                            <cover_url>http://p6-dcd.byteimg.com/img/mosaic-legacy/bef6000051281fce776c~240x0.png</cover_url>
                            <lightappid_pic_url>tt3ed7486aa1fd80c3</lightappid_pic_url>
                            <series_id>3368</series_id>
                            <pc_detail_url>https://www.dongchedi.com/auto/series/3368</pc_detail_url>
                            <lightappid_detail_url>tt3ed7486aa1fd80c3</lightappid_detail_url>
                            <series_offline>0</series_offline>
                            <lightapp_detail_url>pages/seriesIndex?series_id=3368&amp;zt=tt_search_brand&amp;series_name=ENTRANZE</lightapp_detail_url>
                            <detail_url>https://m.dcdapp.com/motor/m/car_series/index?zt=tt_search_brand&amp;series_id=3368</detail_url>
                            <pic_url>https://m.dcdapp.com/motor/m/car_series/atlas?zt=tt_search_brand&amp;series_id=3368&amp;category=wg</pic_url>
                        </item>
                    </series_list>
                </item>
            </sub_brands>
            <lightapp_brand_url>pages/seriesList?zt=tt_search_brand&amp;brand_id=242&amp;brand_name=%E5%B9%BF%E6%B1%BD%E5%9F%83%E5%AE%89</lightapp_brand_url>
        </display>
        <key>广汽埃安新能源</key>
    </item>
    <item>
        <display>
            <title>Conquest新能源</title>
            <pc_brand_url>https://www.dongchedi.com/auto/library/x-x-x-x-x-x-x-x-x-x-x?key=brand&amp;param=316&amp;text=Conquest</pc_brand_url>
            <lightappid_brand_url>tt3ed7486aa1fd80c3</lightappid_brand_url>
            <brand_url>https://m.dcdapp.com/motor/m/car_series/list?zt=tt_search_brand&amp;brand_id=316</brand_url>
            <sub_brands>
                <item>
                    <tag>SUV</tag>
                    <sub_brand_name>Conquest新能源</sub_brand_name>
                    <series_list>
                        <item>
                            <pc_pic_url>https://www.dongchedi.com/auto/series/4050/images</pc_pic_url>
                            <series_brand>Conquest</series_brand>
                            <hot>259</hot>
                            <series_type>1</series_type>
                            <price>未上市</price>
                            <series_name>Knight XV </series_name>
                            <lightapp_pic_url>pages/atlas?series_id=4050&amp;zt=tt_search_brand&amp;series_name=Knight%20XV%20</lightapp_pic_url>
                            <cover_url>http://p3-dcd.byteimg.com/img/motor-img/25ee89bb82720e5d92cfb6b8b12316c6~240x0.png</cover_url>
                            <lightappid_pic_url>tt3ed7486aa1fd80c3</lightappid_pic_url>
                            <series_id>4050</series_id>
                            <pc_detail_url>https://www.dongchedi.com/auto/series/4050</pc_detail_url>
                            <lightappid_detail_url>tt3ed7486aa1fd80c3</lightappid_detail_url>
                            <series_offline>0</series_offline>
                            <lightapp_detail_url>pages/seriesIndex?series_id=4050&amp;zt=tt_search_brand&amp;series_name=Knight%20XV%20</lightapp_detail_url>
                            <detail_url>https://m.dcdapp.com/motor/m/car_series/index?zt=tt_search_brand&amp;series_id=4050</detail_url>
                            <pic_url>https://m.dcdapp.com/motor/m/car_series/atlas?zt=tt_search_brand&amp;series_id=4050&amp;category=wg</pic_url>
                        </item>
                        <item>
                            <pc_pic_url>https://www.dongchedi.com/auto/series/4045/images</pc_pic_url>
                            <series_brand>Conquest</series_brand>
                            <hot>110</hot>
                            <series_type>1</series_type>
                            <price>未上市</price>
                            <series_name>Evada </series_name>
                            <lightapp_pic_url>pages/atlas?series_id=4045&amp;zt=tt_search_brand&amp;series_name=Evada%20</lightapp_pic_url>
                            <cover_url>http://p1-dcd.byteimg.com/img/motor-img/4e3b3117e77943cf64db4217cf0aecbe~240x0.png</cover_url>
                            <lightappid_pic_url>tt3ed7486aa1fd80c3</lightappid_pic_url>
                            <series_id>4045</series_id>
                            <pc_detail_url>https://www.dongchedi.com/auto/series/4045</pc_detail_url>
                            <lightappid_detail_url>tt3ed7486aa1fd80c3</lightappid_detail_url>
                            <series_offline>0</series_offline>
                            <lightapp_detail_url>pages/seriesIndex?series_id=4045&amp;zt=tt_search_brand&amp;series_name=Evada%20</lightapp_detail_url>
                            <detail_url>https://m.dcdapp.com/motor/m/car_series/index?zt=tt_search_brand&amp;series_id=4045</detail_url>
                            <pic_url>https://m.dcdapp.com/motor/m/car_series/atlas?zt=tt_search_brand&amp;series_id=4045&amp;category=wg</pic_url>
                        </item>
                    </series_list>
                </item>
            </sub_brands>
            <lightapp_brand_url>pages/seriesList?zt=tt_search_brand&amp;brand_id=316&amp;brand_name=Conquest</lightapp_brand_url>
        </display>
        <key>conquest新能源</key>
    </item>
    <item>
        <display>
            <title>FMAuto新能源</title>
            <pc_brand_url>https://www.dongchedi.com/auto/library/x-x-x-x-x-x-x-x-x-x-x?key=brand&amp;param=317&amp;text=FM Auto</pc_brand_url>
            <lightappid_brand_url>tt3ed7486aa1fd80c3</lightappid_brand_url>
            <brand_url>https://m.dcdapp.com/motor/m/car_series/list?zt=tt_search_brand&amp;brand_id=317</brand_url>
            <sub_brands>
                <item>
                    <tag>跑车</tag>
                    <sub_brand_name>FMAuto新能源</sub_brand_name>
                    <series_list>
                        <item>
                            <pc_pic_url>https://www.dongchedi.com/auto/series/4047/images</pc_pic_url>
                            <series_brand>FM Auto</series_brand>
                            <hot>131</hot>
                            <series_type>4</series_type>
                            <price>未上市</price>
                            <series_name>Evantra</series_name>
                            <lightapp_pic_url>pages/atlas?series_id=4047&amp;zt=tt_search_brand&amp;series_name=Evantra</lightapp_pic_url>
                            <cover_url>http://p6-dcd.byteimg.com/img/motor-img/a69381d1355498a8ea582b716c0e6bab~240x0.png</cover_url>
                            <lightappid_pic_url>tt3ed7486aa1fd80c3</lightappid_pic_url>
                            <series_id>4047</series_id>
                            <pc_detail_url>https://www.dongchedi.com/auto/series/4047</pc_detail_url>
                            <lightappid_detail_url>tt3ed7486aa1fd80c3</lightappid_detail_url>
                            <series_offline>0</series_offline>
                            <lightapp_detail_url>pages/seriesIndex?series_id=4047&amp;zt=tt_search_brand&amp;series_name=Evantra</lightapp_detail_url>
                            <detail_url>https://m.dcdapp.com/motor/m/car_series/index?zt=tt_search_brand&amp;series_id=4047</detail_url>
                            <pic_url>https://m.dcdapp.com/motor/m/car_series/atlas?zt=tt_search_brand&amp;series_id=4047&amp;category=wg</pic_url>
                        </item>
                    </series_list>
                </item>
            </sub_brands>
            <lightapp_brand_url>pages/seriesList?zt=tt_search_brand&amp;brand_id=317&amp;brand_name=FM%20Auto</lightapp_brand_url>
        </display>
        <key>fmauto新能源</key>
    </item>
    <item>
        <display>
            <title>东风·瑞泰特新能源</title>
            <pc_brand_url>https://www.dongchedi.com/auto/library/x-x-x-x-x-x-x-x-x-x-x?key=brand&amp;param=230&amp;text=东风·瑞泰特</pc_brand_url>
            <lightappid_brand_url>tt3ed7486aa1fd80c3</lightappid_brand_url>
            <brand_url>https://m.dcdapp.com/motor/m/car_series/list?zt=tt_search_brand&amp;brand_id=230</brand_url>
            <sub_brands>
                <item>
                    <tag>轻客</tag>
                    <sub_brand_name>西安新青年新能源</sub_brand_name>
                    <series_list>
                        <item>
                            <pc_pic_url>https://www.dongchedi.com/auto/series/3012/images</pc_pic_url>
                            <series_brand>西安新青年</series_brand>
                            <hot>527</hot>
                            <series_type>6</series_type>
                            <price>7.98万起</price>
                            <series_name>东风·瑞泰特EM10</series_name>
                            <lightapp_pic_url>pages/atlas?series_id=3012&amp;zt=tt_search_brand&amp;series_name=%E4%B8%9C%E9%A3%8E%C2%B7%E7%91%9E%E6%B3%B0%E7%89%B9EM10</lightapp_pic_url>
                            <cover_url>http://p9-dcd.byteimg.com/img/mosaic-legacy/9b130001225dfd683c72~240x0.png</cover_url>
                            <lightappid_pic_url>tt3ed7486aa1fd80c3</lightappid_pic_url>
                            <series_id>3012</series_id>
                            <pc_detail_url>https://www.dongchedi.com/auto/series/3012</pc_detail_url>
                            <lightappid_detail_url>tt3ed7486aa1fd80c3</lightappid_detail_url>
                            <series_offline>0</series_offline>
                            <lightapp_detail_url>pages/seriesIndex?series_id=3012&amp;zt=tt_search_brand&amp;series_name=%E4%B8%9C%E9%A3%8E%C2%B7%E7%91%9E%E6%B3%B0%E7%89%B9EM10</lightapp_detail_url>
                            <detail_url>https://m.dcdapp.com/motor/m/car_series/index?zt=tt_search_brand&amp;series_id=3012</detail_url>
                            <pic_url>https://m.dcdapp.com/motor/m/car_series/atlas?zt=tt_search_brand&amp;series_id=3012&amp;category=wg</pic_url>
                        </item>
                        <item>
                            <pc_pic_url>https://www.dongchedi.com/auto/series/2796/images</pc_pic_url>
                            <series_brand>西安新青年</series_brand>
                            <hot>94</hot>
                            <series_type>6</series_type>
                            <price>25.98万起</price>
                            <series_name>东风·瑞泰特EM30</series_name>
                            <lightapp_pic_url>pages/atlas?series_id=2796&amp;zt=tt_search_brand&amp;series_name=%E4%B8%9C%E9%A3%8E%C2%B7%E7%91%9E%E6%B3%B0%E7%89%B9EM30</lightapp_pic_url>
                            <cover_url>http://p9-dcd.byteimg.com/img/mosaic-legacy/bef300009836014ad858~240x0.png</cover_url>
                            <lightappid_pic_url>tt3ed7486aa1fd80c3</lightappid_pic_url>
                            <series_id>2796</series_id>
                            <pc_detail_url>https://www.dongchedi.com/auto/series/2796</pc_detail_url>
                            <lightappid_detail_url>tt3ed7486aa1fd80c3</lightappid_detail_url>
                            <series_offline>0</series_offline>
                            <lightapp_detail_url>pages/seriesIndex?series_id=2796&amp;zt=tt_search_brand&amp;series_name=%E4%B8%9C%E9%A3%8E%C2%B7%E7%91%9E%E6%B3%B0%E7%89%B9EM30</lightapp_detail_url>
                            <detail_url>https://m.dcdapp.com/motor/m/car_series/index?zt=tt_search_brand&amp;series_id=2796</detail_url>
                            <pic_url>https://m.dcdapp.com/motor/m/car_series/atlas?zt=tt_search_brand&amp;series_id=2796&amp;category=wg</pic_url>
                        </item>
                    </series_list>
                </item>
            </sub_brands>
            <lightapp_brand_url>pages/seriesList?zt=tt_search_brand&amp;brand_id=230&amp;brand_name=%E4%B8%9C%E9%A3%8E%C2%B7%E7%91%9E%E6%B3%B0%E7%89%B9</lightapp_brand_url>
        </display>
        <key>东风·瑞泰特新能源</key>
    </item>
</DOCUMENT>
